[
    {
      "name": "Anderson Komi Havah",
      "email": "anderson@example.com",
      "phone": "123-456-7890"
    },
    {
      "name": "Nirintsoa Liva Jhonson Rabariharinjaka",
      "email": "nirintsoa@example.com",
      "phone": "234-567-8901"
    },
    {
      "name": "Luis Eleazar Lizano Rojas",
      "email": "luis@example.com",
      "phone": "345-678-9012"
    },
    {
      "name": "Javiera Millarai Lorca Jimenez",
      "email": "javiera@example.com",
      "phone": "456-789-0123"
    },
    {
      "name": "Jose Luis Izelo Mabarak",
      "email": "jose@example.com",
      "phone": "567-890-1234"
    }
  ]
  